Zotero_meta_update-0.1.1.data/scripts/update_zotero_meta
work/__init__.py
work/conference_paper.py
work/journal_paper.py
work/lookup.py
work/preprint.py
work/search_item.py
work/utils.py
work/work.py
zotero/__init__.py
zotero/metadata.py
zotero/request.py
Zotero_meta_update-0.1.1.dist-info/LICENSE
Zotero_meta_update-0.1.1.dist-info/METADATA
Zotero_meta_update-0.1.1.dist-info/WHEEL
Zotero_meta_update-0.1.1.dist-info/top_level.txt
Zotero_meta_update-0.1.1.dist-info/RECORD
