Metadata-Version: 2.1
Name: Zotero-meta-update
Version: 0.1.1
Home-page: https://github.com/lizeyan/Zotero-meta-update
Author: Zeyan Li
Author-email: li_zeyan@icloud.com
License: MIT
Project-URL: Bug Tracker, https://github.com/lizeyan/Zotero-meta-update/issues
Project-URL: Source Code, https://github.com/lizeyan/Zotero-meta-update
Classifier: Programming Language :: Python :: 3
Classifier: License :: OSI Approved :: MIT License
Classifier: Operating System :: OS Independent
Requires-Python: >=3.10
License-File: LICENSE
Requires-Dist: loguru (~=0.6.0)
Requires-Dist: requests (~=2.28.1)
Requires-Dist: pytest (~=7.2.0)
Requires-Dist: click (~=8.1.3)
Requires-Dist: pytz
